{
    "trackingEnable": true,
    "foregroundLocationServiceEnable": true,
    "modeHighFrequencyLocation": true,

    "visitEnable": false,
    "classificationEnable": false,
    "minDurationVisitDisplay": null,
    "radiusDetectionClassifiedZOI": null,
    "distanceDetectionThresholdVisits": null,
    "creationOfZOIEnable": false,
    "accuracyVisitFilter": null,

    "currentLocationTimeFilter": 0,
    "currentLocationDistanceFilter": 0,
    "accuracyFilter": 100,

    "searchAPIEnable": false,
    "searchAPICreationRegionEnable": false,
    "searchAPITimeFilter": 0,
    "searchAPIDistanceFilter": 0,

    "distanceProvider": "WoosmapDistance",
    "distanceAPIEnable": false,
    "modeDistance": "driving",
    "trafficDistanceRouting": "fastest",
    "distanceUnits": "metric",
    "distanceLanguage": "en",
    "outOfTimeDelay": 300,
    "dataDurationDelay": 30
}
